odoo/addons/contract_forecast_variable_quantity/README.rst
odoo/addons/contract_forecast_variable_quantity/__init__.py
odoo/addons/contract_forecast_variable_quantity/__manifest__.py
odoo/addons/contract_forecast_variable_quantity/i18n/contract_forecast_variable_quantity.pot
odoo/addons/contract_forecast_variable_quantity/i18n/fr.po
odoo/addons/contract_forecast_variable_quantity/i18n/it.po
odoo/addons/contract_forecast_variable_quantity/i18n/pt_BR.po
odoo/addons/contract_forecast_variable_quantity/i18n/sv.po
odoo/addons/contract_forecast_variable_quantity/models/__init__.py
odoo/addons/contract_forecast_variable_quantity/models/contract_line.py
odoo/addons/contract_forecast_variable_quantity/readme/CONTRIBUTORS.md
odoo/addons/contract_forecast_variable_quantity/readme/DESCRIPTION.md
odoo/addons/contract_forecast_variable_quantity/static/description/icon.png
odoo/addons/contract_forecast_variable_quantity/static/description/index.html
odoo/addons/contract_forecast_variable_quantity/tests/__init__.py
odoo/addons/contract_forecast_variable_quantity/tests/test_contract.py
odoo_addon_contract_forecast_variable_quantity-18.0.1.0.0.8.dist-info/METADATA
odoo_addon_contract_forecast_variable_quantity-18.0.1.0.0.8.dist-info/WHEEL
odoo_addon_contract_forecast_variable_quantity-18.0.1.0.0.8.dist-info/top_level.txt
odoo_addon_contract_forecast_variable_quantity-18.0.1.0.0.8.dist-info/RECORD
